django_user_auth
