Metadata-Version: 2.1
Name: django-user-auth
Version: 0.1.1
Summary: 0.1.0 实现了域用户登录
Home-page: https://www.cnblogs.com/Evan-fanfan/
Author: evanyang
Author-email: lightyiyi@qq.com
License: MIT tencent_message
Platform: UNKNOWN
